open_proxy/__init__.py
open_proxy/open_proxy.py
open_proxy-0.0.2.dist-info/LICENSE.txt
open_proxy-0.0.2.dist-info/METADATA
open_proxy-0.0.2.dist-info/WHEEL
open_proxy-0.0.2.dist-info/top_level.txt
open_proxy-0.0.2.dist-info/RECORD
