Metadata-Version: 2.1
Name: open-proxy
Version: 0.0.2
Summary: Get Free working proxies around the world.
Home-page: https://github.com/santhoshtk01/open-proxy
Author: T.K.santhosh
Author-email: python.santhosh.py@gmail.com
Project-URL: repository, https://github.com/santhoshtk01/open-proxy
Classifier: Programming Language :: Python :: 3
Classifier: License :: OSI Approved :: MIT License
Classifier: Operating System :: OS Independent
Requires-Python: >=3.6
License-File: LICENSE.txt
